<survey GUID="ec55bcbb-08bb-454d-855a-780350795572" Visible="true" GeoTypeTreeNodeExpanded="true" GeoCorrespondenceTreeNodeExpanded="false" name="mat2009" DisplayName="Estad&#237;stica de Matrimonios 2009" year="2009" Categories="">
  <Description><![CDATA[]]></Description>
  <notes><![CDATA[]]></notes>
  <PrivateNotes><![CDATA[]]></PrivateNotes>
  <documentation Label="Documentation">
    <documentlinks/>
  </documentation>
  <geoTypes>
    <geoType GUID="dd0c140a-9f75-403f-a626-0ea8926cc656" Name="SL010" Label="TOTAL" QLabel="TOTAL" RelevantGeoIDs="FIPS,NAME,QName,TOTAL,CCAA,PROVINCIA,MUNICIPIO" PluralName="TOTAL" fullCoverage="true" majorGeo="true" Indent="0" Sumlev="010" FipsCodeLength="2" FipsCodeFieldName="FIPS" FipsCodePartialFieldName="TOTAL" FipsCodePartialLength="2">
      <Visible>true</Visible>
    </geoType>
    <geoType GUID="8ba28221-f979-4d09-b482-9a5b88b963b1" Name="SL030" Label="CCAA" QLabel="CCAA" RelevantGeoIDs="FIPS,NAME,QName,TOTAL,CCAA,PROVINCIA,MUNICIPIO" PluralName="CCAA" fullCoverage="true" majorGeo="true" Indent="1" Sumlev="030" FipsCodeLength="4" FipsCodeFieldName="FIPS" FipsCodePartialFieldName="CCAA" FipsCodePartialLength="2">
      <Visible>true</Visible>
    </geoType>
    <geoType GUID="00abfd41-ad23-469d-9cf1-947abd33685a" Name="SL040" Label="PROVINCIA" QLabel="PROVINCIA" RelevantGeoIDs="FIPS,NAME,QName,TOTAL,CCAA,PROVINCIA,MUNICIPIO" PluralName="PROVINCIA" fullCoverage="true" majorGeo="true" Indent="2" Sumlev="040" FipsCodeLength="6" FipsCodeFieldName="FIPS" FipsCodePartialFieldName="PROVINCIA" FipsCodePartialLength="2">
      <Visible>true</Visible>
    </geoType>
    <geoType GUID="fa446c4b-17d5-4885-ab04-033ff10a068a" Name="SL050" Label="MUNICIPIO" QLabel="MUNICIPIO" RelevantGeoIDs="FIPS,NAME,QName,TOTAL,CCAA,PROVINCIA,MUNICIPIO" PluralName="MUNICIPIO" fullCoverage="true" majorGeo="true" Indent="3" Sumlev="050" FipsCodeLength="11" FipsCodeFieldName="FIPS" FipsCodePartialFieldName="MUNICIPIO" FipsCodePartialLength="5">
      <Visible>true</Visible>
    </geoType>
  </geoTypes>
  <GeoSurveyDataset GUID="30333492-fb6f-4e5d-9320-6cd760fbb95c" SurveyDatasetTreeNodeExpanded="true" TablesTreeNodeExpanded="true" IterationsTreeNodeExpanded="false" DatasetsTreeNodeExpanded="true" Description="Geographic Summary Count" Visible="false" abbreviation="Geo" name="Geography Summary File" DisplayName="Geography Summary File">
    <DataBibliographicInfo/>
    <notes/>
    <PrivateNotes><![CDATA[]]></PrivateNotes>
    <Description><![CDATA[]]></Description>
    <datasets>
      <dataset GUID="8eaf54fd-f97f-4af3-9e1e-f5581899b48f" GeoTypeName="SL010" DbConnString="Server=prime; database=; uid=none;pwd=none;Connect Timeout=1;Pooling=True" DbName="mat2009" GeoIdDbTableName="mat2009_SL010_001" IsCached="false" DbTableNamePrefix="mat2009_SL010_" DbPrimaryKey="SL010_FIPS" DbCopyCount="1"/>
      <dataset GUID="a5c256b1-c65c-4797-8ede-1cc3fef5cb67" GeoTypeName="SL030" DbConnString="Server=prime; database=; uid=none;pwd=none;Connect Timeout=1;Pooling=True" DbName="mat2009" GeoIdDbTableName="mat2009_SL030_001" IsCached="false" DbTableNamePrefix="mat2009_SL030_" DbPrimaryKey="SL010_FIPS,SL030_FIPS" DbCopyCount="1"/>
      <dataset GUID="e001c8fd-a87f-4608-a3cc-1f596034a850" GeoTypeName="SL040" DbConnString="Server=prime; database=; uid=none;pwd=none;Connect Timeout=1;Pooling=True" DbName="mat2009" GeoIdDbTableName="mat2009_SL040_001" IsCached="false" DbTableNamePrefix="mat2009_SL040_" DbPrimaryKey="SL010_FIPS,SL030_FIPS,SL040_FIPS" DbCopyCount="1"/>
      <dataset GUID="840a058d-f883-44c6-b1e4-191fd784ffb5" GeoTypeName="SL050" DbConnString="Server=prime; database=; uid=none;pwd=none;Connect Timeout=1;Pooling=True" DbName="mat2009" GeoIdDbTableName="mat2009_SL050_001" IsCached="false" DbTableNamePrefix="mat2009_SL050_" DbPrimaryKey="SL010_FIPS,SL030_FIPS,SL040_FIPS,SL050_FIPS" DbCopyCount="1"/>
    </datasets>
    <iterations/>
    <tables>
      <table GUID="4cc24cff-f37a-4bf1-a735-13af14e918f5" VariablesAreExclusive="false" notes="" PrivateNotes="" DollarYear="0" PercentBaseMin="1" name="G001" displayName="G1." title="Geography Identifiers" titleWrapped="Geography Identifiers" titleShort="" universe="none" Visible="false" TreeNodeCollapsed="true" DocSectionLinks="" DataCategories="" ProductTags="" FilterRuleName="" CategoryPriorityOrder="0" ShowOnFirstPageOfCategoryListing="false" DbTableSuffix="001" uniqueTableId="G001" source="" DefaultColumnCaption="" samplingInfo="">
        <OutputFormat TableTitle="" TableUniverse="">
          <Columns/>
        </OutputFormat>
        <variable GUID="82fc38cd-26bc-49f0-a99f-386b705ed184" UVID="" BracketSourceVarGUID="" BracketFromVal="0" BracketToVal="0" BracketType="None" FirstInBracketSet="false" notes="" PrivateNotes="" name="QNAME" label="Qualifying Name" qLabel="" indent="0" dataType="2" dataTypeLength="0" formatting="0" customFormatStr="" FormulaFunctionBodyCSharp="" suppType="0" SuppField="" suppFlags="" aggMethod="0" DocLinksAsString="" AggregationStr="None"/>
        <variable GUID="8e8842de-4038-4629-a38f-eeb95b026700" UVID="" BracketSourceVarGUID="" BracketFromVal="0" BracketToVal="0" BracketType="None" FirstInBracketSet="false" notes="" PrivateNotes="" name="NAME" label="Name of Area" qLabel="" indent="0" dataType="2" dataTypeLength="0" formatting="0" customFormatStr="" FormulaFunctionBodyCSharp="" suppType="0" SuppField="" suppFlags="" aggMethod="0" DocLinksAsString="" AggregationStr="None"/>
        <variable GUID="1e598f2a-1e56-41ce-83ee-4499dd7b072e" UVID="" BracketSourceVarGUID="" BracketFromVal="0" BracketToVal="0" BracketType="None" FirstInBracketSet="false" notes="" PrivateNotes="" name="FIPS" label="FIPS" qLabel="" indent="0" dataType="2" dataTypeLength="0" formatting="0" customFormatStr="" FormulaFunctionBodyCSharp="" suppType="0" SuppField="" suppFlags="" aggMethod="0" DocLinksAsString="" AggregationStr="None"/>
        <variable GUID="e4ba71db-5283-4543-a180-7daea6e5368f" UVID="" BracketSourceVarGUID="" BracketFromVal="0" BracketToVal="0" BracketType="None" FirstInBracketSet="false" notes="" PrivateNotes="" name="TOTAL" label="TOTAL" qLabel="" indent="0" dataType="2" dataTypeLength="0" formatting="0" customFormatStr="" FormulaFunctionBodyCSharp="" suppType="0" SuppField="" suppFlags="" aggMethod="0" DocLinksAsString="" AggregationStr="None"/>
        <variable GUID="249a51a6-ccb5-4906-8c79-27714fe968eb" UVID="" BracketSourceVarGUID="" BracketFromVal="0" BracketToVal="0" BracketType="None" FirstInBracketSet="false" notes="" PrivateNotes="" name="CCAA" label="CCAA" qLabel="" indent="0" dataType="2" dataTypeLength="0" formatting="0" customFormatStr="" FormulaFunctionBodyCSharp="" suppType="0" SuppField="" suppFlags="" aggMethod="0" DocLinksAsString="" AggregationStr="None"/>
        <variable GUID="94a1b1d0-c940-4bc8-8c86-3b2d673a25c8" UVID="" BracketSourceVarGUID="" BracketFromVal="0" BracketToVal="0" BracketType="None" FirstInBracketSet="false" notes="" PrivateNotes="" name="PROVINCIA" label="PROVINCIA" qLabel="" indent="0" dataType="2" dataTypeLength="0" formatting="0" customFormatStr="" FormulaFunctionBodyCSharp="" suppType="0" SuppField="" suppFlags="" aggMethod="0" DocLinksAsString="" AggregationStr="None"/>
        <variable GUID="2b17c16b-2767-480a-a53a-85162727c873" UVID="" BracketSourceVarGUID="" BracketFromVal="0" BracketToVal="0" BracketType="None" FirstInBracketSet="false" notes="" PrivateNotes="" name="MUNICIPIO" label="MUNICIPIO" qLabel="" indent="0" dataType="2" dataTypeLength="0" formatting="0" customFormatStr="" FormulaFunctionBodyCSharp="" suppType="0" SuppField="" suppFlags="" aggMethod="0" DocLinksAsString="" AggregationStr="None"/>
      </table>
    </tables>
  </GeoSurveyDataset>
  <SurveyDatasets>
    <SurveyDataset GUID="278885a1-532a-4660-a39e-4bfd18b5c445" SurveyDatasetTreeNodeExpanded="true" TablesTreeNodeExpanded="true" IterationsTreeNodeExpanded="false" DatasetsTreeNodeExpanded="true" Description="" Visible="false" abbreviation="SE" name="CED Tables" DisplayName="CED Tables">
      <DataBibliographicInfo/>
      <notes/>
      <PrivateNotes><![CDATA[]]></PrivateNotes>
      <Description><![CDATA[]]></Description>
      <datasets>
        <dataset GUID="cd5d9cbf-f30d-4e5f-85f2-2949fba7799e" GeoTypeName="SL010" DbConnString="Server=prime; database=; uid=none;pwd=none;Connect Timeout=1;Pooling=True" DbName="mat2009" GeoIdDbTableName="mat2009_SL010_001" IsCached="false" DbTableNamePrefix="mat2009_SL010_" DbPrimaryKey="SL010_FIPS" DbCopyCount="1"/>
        <dataset GUID="3c62e4d7-48ce-49a4-8381-c35ec0e50733" GeoTypeName="SL030" DbConnString="Server=prime; database=; uid=none;pwd=none;Connect Timeout=1;Pooling=True" DbName="mat2009" GeoIdDbTableName="mat2009_SL030_001" IsCached="false" DbTableNamePrefix="mat2009_SL030_" DbPrimaryKey="SL010_FIPS,SL030_FIPS" DbCopyCount="1"/>
        <dataset GUID="efe62a9d-1134-4a2d-b2b2-0a65737e5f15" GeoTypeName="SL040" DbConnString="Server=prime; database=; uid=none;pwd=none;Connect Timeout=1;Pooling=True" DbName="mat2009" GeoIdDbTableName="mat2009_SL040_001" IsCached="false" DbTableNamePrefix="mat2009_SL040_" DbPrimaryKey="SL010_FIPS,SL030_FIPS,SL040_FIPS" DbCopyCount="1"/>
        <dataset GUID="3141801d-0a79-466f-8039-e97c905e0a49" GeoTypeName="SL050" DbConnString="Server=prime; database=; uid=none;pwd=none;Connect Timeout=1;Pooling=True" DbName="mat2009" GeoIdDbTableName="mat2009_SL050_001" IsCached="false" DbTableNamePrefix="mat2009_SL050_" DbPrimaryKey="SL010_FIPS,SL030_FIPS,SL040_FIPS,SL050_FIPS" DbCopyCount="1"/>
      </datasets>
      <iterations/>
      <tables>
        <!--Insert SE tables here !!!-->
      </tables>
    </SurveyDataset>
    <SurveyDataset GUID="ccace359-b971-4505-a5ad-2941eb92a933" SurveyDatasetTreeNodeExpanded="true" TablesTreeNodeExpanded="true" IterationsTreeNodeExpanded="false" DatasetsTreeNodeExpanded="true" Description="" Visible="true" abbreviation="ORG" name="Original Tables" DisplayName="Original Tables">
      <DataBibliographicInfo/>
      <notes/>
      <PrivateNotes><![CDATA[]]></PrivateNotes>
      <Description><![CDATA[]]></Description>
      <datasets>
        <dataset GUID="f62d1684-ab7f-427c-bb82-228f7d5d1ab2" GeoTypeName="SL010" DbConnString="Server=prime; database=; uid=none;pwd=none;Connect Timeout=1;Pooling=True" DbName="mat2009" GeoIdDbTableName="mat2009_SL010_001" IsCached="false" DbTableNamePrefix="mat2009_SL010_" DbPrimaryKey="SL010_FIPS" DbCopyCount="1"/>
        <dataset GUID="91d57ae5-169f-444d-a482-66ad3f58cca2" GeoTypeName="SL030" DbConnString="Server=prime; database=; uid=none;pwd=none;Connect Timeout=1;Pooling=True" DbName="mat2009" GeoIdDbTableName="mat2009_SL030_001" IsCached="false" DbTableNamePrefix="mat2009_SL030_" DbPrimaryKey="SL010_FIPS,SL030_FIPS" DbCopyCount="1"/>
        <dataset GUID="bae5d899-53cf-4820-9a3d-f6da83a23f60" GeoTypeName="SL040" DbConnString="Server=prime; database=; uid=none;pwd=none;Connect Timeout=1;Pooling=True" DbName="mat2009" GeoIdDbTableName="mat2009_SL040_001" IsCached="false" DbTableNamePrefix="mat2009_SL040_" DbPrimaryKey="SL010_FIPS,SL030_FIPS,SL040_FIPS" DbCopyCount="1"/>
        <dataset GUID="eb437713-70e2-4828-ac37-86b258431c42" GeoTypeName="SL050" DbConnString="Server=prime; database=; uid=none;pwd=none;Connect Timeout=1;Pooling=True" DbName="mat2009" GeoIdDbTableName="mat2009_SL050_001" IsCached="false" DbTableNamePrefix="mat2009_SL050_" DbPrimaryKey="SL010_FIPS,SL030_FIPS,SL040_FIPS,SL050_FIPS" DbCopyCount="1"/>
      </datasets>
      <iterations/>
      <tables>
        <table GUID="64a9667e-f054-411b-b099-e7b58de5c1b3" VariablesAreExclusive="false" DollarYear="0" PercentBaseMin="1" name="mat2009_001" displayName="mat2009_001" title="Matrimonios de distinto sexo por tipo de celebraci&#243;n" titleWrapped="Matrimonios de distinto sexo por tipo de celebraci&#243;n" universe="none" Visible="true" TreeNodeCollapsed="false" CategoryPriorityOrder="0" ShowOnFirstPageOfCategoryListing="false" DbTableSuffix="001" uniqueTableId="mat2009_001" notes="" PrivateNotes="" TableMapInfo="" titleShort="" VisibleInMaps="true" DocSectionLinks="" DataCategories="Matrimonios;" ProductTags="" FilterRuleName="" PaletteType="" PaletteInverse="false" PaletteName="" source="mat2011_001" DefaultColumnCaption="" samplingInfo="">
          <OutputFormat TableTitle="" TableUniverse="">
            <Columns/>
          </OutputFormat>
          <variable GUID="addd5a9f-3604-47dc-9c39-2e8603610133" UVID="" BracketSourceVarGUID="" BracketFromVal="0" BracketToVal="0" BracketType="None" FirstInBracketSet="false" notes="" PrivateNotes="" name="mat2009_001_MAT_V1" label="Total matrimonios" qLabel="Total matrimonios" indent="0" dataType="4" dataTypeLength="0" formatting="9" customFormatStr="" FormulaFunctionBodyCSharp="" suppType="0" SuppField="" suppFlags="" aggMethod="1" DocLinksAsString="" AggregationStr="Add" BubbleSizeHint="1" FR="" PN="" PT=""/>
          <variable GUID="18e1698f-3cfe-4d35-9aa3-f356c03bce37" UVID="" BracketSourceVarGUID="" BracketFromVal="0" BracketToVal="0" BracketType="None" FirstInBracketSet="false" notes="" PrivateNotes="" name="mat2009_001_MAT_V2" label="Cat&#243;lico" qLabel="" indent="1" dataType="4" dataTypeLength="0" formatting="9" customFormatStr="" FormulaFunctionBodyCSharp="" suppType="0" SuppField="" suppFlags="" aggMethod="1" DocLinksAsString="" AggregationStr="Add" BubbleSizeHint="1" FR="DECIL_SPAIN" PN="" PT=""/>
          <variable GUID="acc5b4b7-3920-4230-91ae-5a5508d09087" UVID="" BracketSourceVarGUID="" BracketFromVal="0" BracketToVal="0" BracketType="None" FirstInBracketSet="false" notes="" PrivateNotes="" name="mat2009_001_MAT_V3" label="Otra religi&#243;n" qLabel="" indent="1" dataType="4" dataTypeLength="0" formatting="9" customFormatStr="" FormulaFunctionBodyCSharp="" suppType="0" SuppField="" suppFlags="" aggMethod="1" DocLinksAsString="" AggregationStr="Add" BubbleSizeHint="1" FR="DECIL_SPAIN" PN="" PT=""/>
          <variable GUID="f3cccb1a-c0ce-4dc8-ad6d-663e22656fb5" UVID="" BracketSourceVarGUID="" BracketFromVal="0" BracketToVal="0" BracketType="None" FirstInBracketSet="false" notes="" PrivateNotes="" name="mat2009_001_MAT_V4" label="Civil" qLabel="" indent="1" dataType="4" dataTypeLength="0" formatting="9" customFormatStr="" FormulaFunctionBodyCSharp="" suppType="0" SuppField="" suppFlags="" aggMethod="1" DocLinksAsString="" AggregationStr="Add" BubbleSizeHint="1" FR="DECIL_SPAIN" PN="" PT=""/>
        </table>
      </tables>
      <tables>
        <table GUID="1d8e1baf-f169-468d-a0a1-af8e8a5ef9fa" VariablesAreExclusive="false" DollarYear="0" PercentBaseMin="1" name="mat2009_002" displayName="mat2009_002" title="Matrimonios de distinto sexo por lugar de residencia anterior" titleWrapped="Matrimonios de distinto sexo por lugar de residencia anterior" universe="none" Visible="true" TreeNodeCollapsed="false" CategoryPriorityOrder="0" ShowOnFirstPageOfCategoryListing="false" DbTableSuffix="002" uniqueTableId="mat2009_002" notes="" PrivateNotes="" TableMapInfo="" titleShort="" VisibleInMaps="true" DocSectionLinks="" DataCategories="Matrimonios;" ProductTags="" FilterRuleName="" PaletteType="" PaletteInverse="false" PaletteName="" source="mat2011_002" DefaultColumnCaption="" samplingInfo="">
          <OutputFormat TableTitle="" TableUniverse="">
            <Columns/>
          </OutputFormat>
          <variable GUID="6eeb6382-3e0f-46f2-9062-9fc43fe6ac5f" UVID="" BracketSourceVarGUID="" BracketFromVal="0" BracketToVal="0" BracketType="None" FirstInBracketSet="false" notes="" PrivateNotes="" name="mat2009_002_MAT_V5" label="Matrimonios" qLabel="Matrimonios" indent="0" dataType="4" dataTypeLength="0" formatting="9" customFormatStr="" FormulaFunctionBodyCSharp="" suppType="0" SuppField="" suppFlags="" aggMethod="1" DocLinksAsString="" AggregationStr="Add" BubbleSizeHint="1" FR="" PN="" PT=""/>
          <variable GUID="e3fe8511-6d0d-4b50-8b27-da2151ca4c88" UVID="" BracketSourceVarGUID="" BracketFromVal="0" BracketToVal="0" BracketType="None" FirstInBracketSet="false" notes="" PrivateNotes="" name="mat2009_002_MAT_V6" label="Ambos c&#243;nyuges resid&#237;an mismo municipio" qLabel="Ambos c&#243;nyuges resid&#237;an mismo municipio" indent="1" dataType="4" dataTypeLength="0" formatting="9" customFormatStr="" FormulaFunctionBodyCSharp="" suppType="0" SuppField="" suppFlags="" aggMethod="1" DocLinksAsString="" AggregationStr="Add" BubbleSizeHint="1" FR="DECIL_SPAIN" PN="" PT=""/>
          <variable GUID="921f7288-608c-446e-a3b9-10ecd85088ca" UVID="" BracketSourceVarGUID="" BracketFromVal="0" BracketToVal="0" BracketType="None" FirstInBracketSet="false" notes="" PrivateNotes="" name="mat2009_002_MAT_V7" label="Uno de los c&#243;nyuges resid&#237;a en el municipio" qLabel="Uno de los c&#243;nyuges resid&#237;a en el municipio" indent="1" dataType="4" dataTypeLength="0" formatting="9" customFormatStr="" FormulaFunctionBodyCSharp="" suppType="0" SuppField="" suppFlags="" aggMethod="1" DocLinksAsString="" AggregationStr="Add" BubbleSizeHint="1" FR="DECIL_SPAIN" PN="" PT=""/>
          <variable GUID="95014bc9-09c6-4293-a690-77405e543d28" UVID="" BracketSourceVarGUID="" BracketFromVal="0" BracketToVal="0" BracketType="None" FirstInBracketSet="false" notes="" PrivateNotes="" name="mat2009_002_MAT_V8" label="Ning&#250;n c&#243;nyuge resid&#237;a en el municipio" qLabel="Ning&#250;n c&#243;nyuge resid&#237;a en el municipio" indent="1" dataType="4" dataTypeLength="0" formatting="9" customFormatStr="" FormulaFunctionBodyCSharp="" suppType="0" SuppField="" suppFlags="" aggMethod="1" DocLinksAsString="" AggregationStr="Add" BubbleSizeHint="1" FR="DECIL_SPAIN" PN="" PT=""/>
        </table>
      </tables>
      <tables>
        <table GUID="40236578-0e14-4c69-9fc2-0cd73588cb3f" VariablesAreExclusive="false" DollarYear="0" PercentBaseMin="1" name="mat2009_003" displayName="mat2009_003" title="Matrimonios de distinto sexo por estado civil" titleWrapped="Matrimonios de distinto sexo por estado civil" universe="none" Visible="true" TreeNodeCollapsed="false" CategoryPriorityOrder="0" ShowOnFirstPageOfCategoryListing="false" DbTableSuffix="003" uniqueTableId="mat2009_003" notes="" PrivateNotes="" TableMapInfo="" titleShort="" VisibleInMaps="true" DocSectionLinks="" DataCategories="Matrimonios;" ProductTags="" FilterRuleName="" PaletteType="" PaletteInverse="false" PaletteName="" source="mat2011_003" DefaultColumnCaption="" samplingInfo="">
          <OutputFormat TableTitle="" TableUniverse="">
            <Columns/>
          </OutputFormat>
          <variable GUID="9b5eaab1-275c-4b91-b7b5-894e48c61b1a" UVID="" BracketSourceVarGUID="" BracketFromVal="0" BracketToVal="0" BracketType="None" FirstInBracketSet="false" notes="" PrivateNotes="" name="mat2009_003_MAT_V9" label="Matrimonios" qLabel="Matrimonios" indent="0" dataType="4" dataTypeLength="0" formatting="9" customFormatStr="" FormulaFunctionBodyCSharp="" suppType="0" SuppField="" suppFlags="" aggMethod="1" DocLinksAsString="" AggregationStr="Add" BubbleSizeHint="1" FR="" PN="" PT=""/>
          <variable GUID="93396195-3235-4f10-beaf-cebfa3df2073" UVID="" BracketSourceVarGUID="" BracketFromVal="0" BracketToVal="0" BracketType="None" FirstInBracketSet="false" notes="" PrivateNotes="" name="mat2009_003_MAT_V10" label="Hombres solteros" qLabel="Hombres solteros" indent="1" dataType="4" dataTypeLength="0" formatting="9" customFormatStr="" FormulaFunctionBodyCSharp="" suppType="0" SuppField="" suppFlags="" aggMethod="1" DocLinksAsString="" AggregationStr="Add" BubbleSizeHint="1" FR="DECIL_SPAIN" PN="" PT=""/>
          <variable GUID="5a838d7c-0d64-4fba-90ab-27c0fa9598d1" UVID="" BracketSourceVarGUID="" BracketFromVal="0" BracketToVal="0" BracketType="None" FirstInBracketSet="false" notes="" PrivateNotes="" name="mat2009_003_MAT_V11" label="Hombres viudos" qLabel="Hombres viudos" indent="1" dataType="4" dataTypeLength="0" formatting="9" customFormatStr="" FormulaFunctionBodyCSharp="" suppType="0" SuppField="" suppFlags="" aggMethod="1" DocLinksAsString="" AggregationStr="Add" BubbleSizeHint="1" FR="DECIL_SPAIN" PN="" PT=""/>
          <variable GUID="6a144f1c-2e30-4bcb-91ae-202c9dea750b" UVID="" BracketSourceVarGUID="" BracketFromVal="0" BracketToVal="0" BracketType="None" FirstInBracketSet="false" notes="" PrivateNotes="" name="mat2009_003_MAT_V12" label="Hombres divorciados" qLabel="Hombres divorciados" indent="1" dataType="4" dataTypeLength="0" formatting="9" customFormatStr="" FormulaFunctionBodyCSharp="" suppType="0" SuppField="" suppFlags="" aggMethod="1" DocLinksAsString="" AggregationStr="Add" BubbleSizeHint="1" FR="DECIL_SPAIN" PN="" PT=""/>
          <variable GUID="6e0f3e2c-dbfc-47b7-9023-050526b5cb5d" UVID="" BracketSourceVarGUID="" BracketFromVal="0" BracketToVal="0" BracketType="None" FirstInBracketSet="false" notes="" PrivateNotes="" name="mat2009_003_MAT_V13" label="Matrimonios" qLabel="Matrimonios" indent="0" dataType="4" dataTypeLength="0" formatting="9" customFormatStr="" FormulaFunctionBodyCSharp="" suppType="0" SuppField="" suppFlags="" aggMethod="1" DocLinksAsString="" AggregationStr="Add" BubbleSizeHint="1" FR="" PN="" PT=""/>
          <variable GUID="a8ef87dc-ae9f-46fd-ac1d-252463249299" UVID="" BracketSourceVarGUID="" BracketFromVal="0" BracketToVal="0" BracketType="None" FirstInBracketSet="false" notes="" PrivateNotes="" name="mat2009_003_MAT_V14" label="Mujeres solteras" qLabel="Mujeres solteras" indent="1" dataType="4" dataTypeLength="0" formatting="9" customFormatStr="" FormulaFunctionBodyCSharp="" suppType="0" SuppField="" suppFlags="" aggMethod="1" DocLinksAsString="" AggregationStr="Add" BubbleSizeHint="1" FR="DECIL_SPAIN" PN="" PT=""/>
          <variable GUID="ae39d9a2-9b47-4e6c-8569-b31fcada7ba6" UVID="" BracketSourceVarGUID="" BracketFromVal="0" BracketToVal="0" BracketType="None" FirstInBracketSet="false" notes="" PrivateNotes="" name="mat2009_003_MAT_V15" label="Mujeres viudas" qLabel="Mujeres viudas" indent="1" dataType="4" dataTypeLength="0" formatting="9" customFormatStr="" FormulaFunctionBodyCSharp="" suppType="0" SuppField="" suppFlags="" aggMethod="1" DocLinksAsString="" AggregationStr="Add" BubbleSizeHint="1" FR="DECIL_SPAIN" PN="" PT=""/>
          <variable GUID="4343a727-3264-4cfb-8906-b16d29952564" UVID="" BracketSourceVarGUID="" BracketFromVal="0" BracketToVal="0" BracketType="None" FirstInBracketSet="false" notes="" PrivateNotes="" name="mat2009_003_MAT_V16" label="Mujeres divorciadas" qLabel="Mujeres divorciadas" indent="1" dataType="4" dataTypeLength="0" formatting="9" customFormatStr="" FormulaFunctionBodyCSharp="" suppType="0" SuppField="" suppFlags="" aggMethod="1" DocLinksAsString="" AggregationStr="Add" BubbleSizeHint="1" FR="DECIL_SPAIN" PN="" PT=""/>
        </table>
      </tables>
      <tables>
        <table GUID="cf6105c7-a910-4dba-8ad7-9b38e859c81c" VariablesAreExclusive="false" DollarYear="0" PercentBaseMin="1" name="mat2009_004" displayName="mat2009_004" title="Matrimonios de distinto sexo por nacionalidad" titleWrapped="Matrimonios de distinto sexo por nacionalidad" universe="none" Visible="true" TreeNodeCollapsed="false" CategoryPriorityOrder="0" ShowOnFirstPageOfCategoryListing="false" DbTableSuffix="004" uniqueTableId="mat2009_004" notes="" PrivateNotes="" TableMapInfo="" titleShort="" VisibleInMaps="true" DocSectionLinks="" DataCategories="Matrimonios;" ProductTags="" FilterRuleName="" PaletteType="" PaletteInverse="false" PaletteName="" source="mat2011_004" DefaultColumnCaption="" samplingInfo="">
          <OutputFormat TableTitle="" TableUniverse="">
            <Columns/>
          </OutputFormat>
          <variable GUID="87d45c93-f612-400a-8100-f9ea961044a9" UVID="" BracketSourceVarGUID="" BracketFromVal="0" BracketToVal="0" BracketType="None" FirstInBracketSet="false" notes="" PrivateNotes="" name="mat2009_004_MAT_V17" label="Matrimonios" qLabel="Matrimonios" indent="0" dataType="4" dataTypeLength="0" formatting="9" customFormatStr="" FormulaFunctionBodyCSharp="" suppType="0" SuppField="" suppFlags="" aggMethod="1" DocLinksAsString="" AggregationStr="Add" BubbleSizeHint="1" FR="" PN="" PT=""/>
          <variable GUID="c249565a-fc31-42f3-8f9c-a4e16610a0bd" UVID="" BracketSourceVarGUID="" BracketFromVal="0" BracketToVal="0" BracketType="None" FirstInBracketSet="false" notes="" PrivateNotes="" name="mat2009_004_MAT_V18" label="Ambos c&#243;nguyes espa&#241;oles" qLabel="Ambos c&#243;nguyes espa&#241;oles" indent="1" dataType="4" dataTypeLength="0" formatting="9" customFormatStr="" FormulaFunctionBodyCSharp="" suppType="0" SuppField="" suppFlags="" aggMethod="1" DocLinksAsString="" AggregationStr="Add" BubbleSizeHint="1" FR="DECIL_SPAIN" PN="" PT=""/>
          <variable GUID="a550e3ed-5c0b-4926-93aa-dfc861de760d" UVID="" BracketSourceVarGUID="" BracketFromVal="0" BracketToVal="0" BracketType="None" FirstInBracketSet="false" notes="" PrivateNotes="" name="mat2009_004_MAT_V19" label="Hombre espa&#241;ol y mujer extranjera" qLabel="Hombre espa&#241;ol y mujer extranjera" indent="1" dataType="4" dataTypeLength="0" formatting="9" customFormatStr="" FormulaFunctionBodyCSharp="" suppType="0" SuppField="" suppFlags="" aggMethod="1" DocLinksAsString="" AggregationStr="Add" BubbleSizeHint="1" FR="DECIL_SPAIN" PN="" PT=""/>
          <variable GUID="41ebb520-0554-489c-ade5-84671ce13565" UVID="" BracketSourceVarGUID="" BracketFromVal="0" BracketToVal="0" BracketType="None" FirstInBracketSet="false" notes="" PrivateNotes="" name="mat2009_004_MAT_V20" label="Hombre extranjero y mujer espa&#241;ola" qLabel="Hombre extranjero y mujer espa&#241;ola" indent="1" dataType="4" dataTypeLength="0" formatting="9" customFormatStr="" FormulaFunctionBodyCSharp="" suppType="0" SuppField="" suppFlags="" aggMethod="1" DocLinksAsString="" AggregationStr="Add" BubbleSizeHint="1" FR="DECIL_SPAIN" PN="" PT=""/>
          <variable GUID="9b4c87a8-1658-4cfc-a78f-28308dd7b84b" UVID="" BracketSourceVarGUID="" BracketFromVal="0" BracketToVal="0" BracketType="None" FirstInBracketSet="false" notes="" PrivateNotes="" name="mat2009_004_MAT_V21" label="Ambos c&#243;nyuges extranjeros" qLabel="Ambos c&#243;nyuges extranjeros" indent="1" dataType="4" dataTypeLength="0" formatting="9" customFormatStr="" FormulaFunctionBodyCSharp="" suppType="0" SuppField="" suppFlags="" aggMethod="1" DocLinksAsString="" AggregationStr="Add" BubbleSizeHint="1" FR="DECIL_SPAIN" PN="" PT=""/>
        </table>
      </tables>
    </SurveyDataset>
  </SurveyDatasets>
  <Categories>
    <string>Matrimonios 2009</string>
  </Categories>
</survey>
