<survey GUID="8db16a58-ffa1-487d-87a4-172ffd1ad5c2" Visible="true" GeoTypeTreeNodeExpanded="true" GeoCorrespondenceTreeNodeExpanded="false" name="SEPE2020" DisplayName="Servicio P&#250;blico de Empleo Estatal 2020" year="2020" Categories="">
  <Description><![CDATA[]]></Description>
  <notes><![CDATA[]]></notes>
  <PrivateNotes><![CDATA[]]></PrivateNotes>
  <documentation Label="Documentation">
    <documentlinks/>
  </documentation>
  <geoTypes>
    <geoType GUID="175d401a-5100-4cc0-ab05-531b3496ae1a" Name="SL010" Label="TOTAL" QLabel="TOTAL" RelevantGeoIDs="FIPS,NAME,QName,TOTAL,CCAA,PROVINCIA,MUNICIPIO" PluralName="TOTAL" fullCoverage="true" majorGeo="true" Indent="0" Sumlev="010" FipsCodeLength="2" FipsCodeFieldName="FIPS" FipsCodePartialFieldName="TOTAL" FipsCodePartialLength="2">
      <Visible>true</Visible>
    </geoType>
    <geoType GUID="92ab495b-aa02-481b-b746-759ff5732b9e" Name="SL030" Label="CCAA" QLabel="CCAA" RelevantGeoIDs="FIPS,NAME,QName,TOTAL,CCAA,PROVINCIA,MUNICIPIO" PluralName="CCAA" fullCoverage="true" majorGeo="true" Indent="1" Sumlev="030" FipsCodeLength="4" FipsCodeFieldName="FIPS" FipsCodePartialFieldName="CCAA" FipsCodePartialLength="2">
      <Visible>true</Visible>
    </geoType>
    <geoType GUID="f3df2cb7-3295-4cb7-9db1-c1aa7470a3e1" Name="SL040" Label="PROVINCIA" QLabel="PROVINCIA" RelevantGeoIDs="FIPS,NAME,QName,TOTAL,CCAA,PROVINCIA,MUNICIPIO" PluralName="PROVINCIA" fullCoverage="true" majorGeo="true" Indent="2" Sumlev="040" FipsCodeLength="6" FipsCodeFieldName="FIPS" FipsCodePartialFieldName="PROVINCIA" FipsCodePartialLength="2">
      <Visible>true</Visible>
    </geoType>
    <geoType GUID="8900631e-a115-4c43-8717-e77b144eab37" Name="SL050" Label="MUNICIPIO" QLabel="MUNICIPIO" RelevantGeoIDs="FIPS,NAME,QName,TOTAL,CCAA,PROVINCIA,MUNICIPIO" PluralName="MUNICIPIO" fullCoverage="true" majorGeo="true" Indent="3" Sumlev="050" FipsCodeLength="11" FipsCodeFieldName="FIPS" FipsCodePartialFieldName="MUNICIPIO" FipsCodePartialLength="5">
      <Visible>true</Visible>
    </geoType>
  </geoTypes>
  <GeoSurveyDataset GUID="3ef1ac16-7a39-4ee4-a886-3987339c7d09" SurveyDatasetTreeNodeExpanded="true" TablesTreeNodeExpanded="true" IterationsTreeNodeExpanded="false" DatasetsTreeNodeExpanded="true" Description="Geographic Summary Count" Visible="false" abbreviation="Geo" name="Geography Summary File" DisplayName="Geography Summary File">
    <DataBibliographicInfo/>
    <notes/>
    <PrivateNotes><![CDATA[]]></PrivateNotes>
    <Description><![CDATA[]]></Description>
    <datasets>
      <dataset GUID="0ab9dde5-d855-4a6c-89fe-a519e5044363" GeoTypeName="SL010" DbConnString="Server=prime; database=; uid=none;pwd=none;Connect Timeout=1;Pooling=True" DbName="SEPE2020" GeoIdDbTableName="SEPE2020_SL010_001" IsCached="false" DbTableNamePrefix="SEPE2020_SL010_" DbPrimaryKey="SL010_FIPS" DbCopyCount="1"/>
      <dataset GUID="9fa70727-cdeb-463a-a79b-a3b29ecb7933" GeoTypeName="SL030" DbConnString="Server=prime; database=; uid=none;pwd=none;Connect Timeout=1;Pooling=True" DbName="SEPE2020" GeoIdDbTableName="SEPE2020_SL030_001" IsCached="false" DbTableNamePrefix="SEPE2020_SL030_" DbPrimaryKey="SL010_FIPS,SL030_FIPS" DbCopyCount="1"/>
      <dataset GUID="75e4659c-a697-4cd6-b356-ea887d01e461" GeoTypeName="SL040" DbConnString="Server=prime; database=; uid=none;pwd=none;Connect Timeout=1;Pooling=True" DbName="SEPE2020" GeoIdDbTableName="SEPE2020_SL040_001" IsCached="false" DbTableNamePrefix="SEPE2020_SL040_" DbPrimaryKey="SL010_FIPS,SL030_FIPS,SL040_FIPS" DbCopyCount="1"/>
      <dataset GUID="3fb7e4c9-83c3-4d2a-b12d-0f5a164656ec" GeoTypeName="SL050" DbConnString="Server=prime; database=; uid=none;pwd=none;Connect Timeout=1;Pooling=True" DbName="SEPE2020" GeoIdDbTableName="SEPE2020_SL050_001" IsCached="false" DbTableNamePrefix="SEPE2020_SL050_" DbPrimaryKey="SL010_FIPS,SL030_FIPS,SL040_FIPS,SL050_FIPS" DbCopyCount="1"/>
    </datasets>
    <iterations/>
    <tables>
      <table GUID="dac3ee2f-0cb1-4b43-ba02-f7279501f2b6" VariablesAreExclusive="false" notes="" PrivateNotes="" DollarYear="0" PercentBaseMin="1" name="G001" displayName="G1." title="Geography Identifiers" titleWrapped="Geography Identifiers" titleShort="" universe="none" Visible="false" TreeNodeCollapsed="true" DocSectionLinks="" DataCategories="" ProductTags="" FilterRuleName="" CategoryPriorityOrder="0" ShowOnFirstPageOfCategoryListing="false" DbTableSuffix="001" uniqueTableId="G001" source="" DefaultColumnCaption="" samplingInfo="">
        <OutputFormat TableTitle="" TableUniverse="">
          <Columns/>
        </OutputFormat>
        <variable GUID="e1c26ff3-6ef4-4751-87ea-58a27ee2024a" UVID="" BracketSourceVarGUID="" BracketFromVal="0" BracketToVal="0" BracketType="None" FirstInBracketSet="false" notes="" PrivateNotes="" name="QNAME" label="Qualifying Name" qLabel="" indent="0" dataType="2" dataTypeLength="0" formatting="0" customFormatStr="" FormulaFunctionBodyCSharp="" suppType="0" SuppField="" suppFlags="" aggMethod="0" DocLinksAsString="" AggregationStr="None"/>
        <variable GUID="204c5fe1-a232-41c7-b688-2bae7a332d63" UVID="" BracketSourceVarGUID="" BracketFromVal="0" BracketToVal="0" BracketType="None" FirstInBracketSet="false" notes="" PrivateNotes="" name="NAME" label="Name of Area" qLabel="" indent="0" dataType="2" dataTypeLength="0" formatting="0" customFormatStr="" FormulaFunctionBodyCSharp="" suppType="0" SuppField="" suppFlags="" aggMethod="0" DocLinksAsString="" AggregationStr="None"/>
        <variable GUID="9c387e14-e8bd-4f82-b6bc-af615a71de23" UVID="" BracketSourceVarGUID="" BracketFromVal="0" BracketToVal="0" BracketType="None" FirstInBracketSet="false" notes="" PrivateNotes="" name="FIPS" label="FIPS" qLabel="" indent="0" dataType="2" dataTypeLength="0" formatting="0" customFormatStr="" FormulaFunctionBodyCSharp="" suppType="0" SuppField="" suppFlags="" aggMethod="0" DocLinksAsString="" AggregationStr="None"/>
        <variable GUID="dd2b875c-ba03-4f2a-b6d9-a86a10c58981" UVID="" BracketSourceVarGUID="" BracketFromVal="0" BracketToVal="0" BracketType="None" FirstInBracketSet="false" notes="" PrivateNotes="" name="TOTAL" label="TOTAL" qLabel="" indent="0" dataType="2" dataTypeLength="0" formatting="0" customFormatStr="" FormulaFunctionBodyCSharp="" suppType="0" SuppField="" suppFlags="" aggMethod="0" DocLinksAsString="" AggregationStr="None"/>
        <variable GUID="3406c07b-491e-4db6-be99-24272321fb5e" UVID="" BracketSourceVarGUID="" BracketFromVal="0" BracketToVal="0" BracketType="None" FirstInBracketSet="false" notes="" PrivateNotes="" name="CCAA" label="CCAA" qLabel="" indent="0" dataType="2" dataTypeLength="0" formatting="0" customFormatStr="" FormulaFunctionBodyCSharp="" suppType="0" SuppField="" suppFlags="" aggMethod="0" DocLinksAsString="" AggregationStr="None"/>
        <variable GUID="daada8dd-9555-483b-b5a4-3ef2e3d51085" UVID="" BracketSourceVarGUID="" BracketFromVal="0" BracketToVal="0" BracketType="None" FirstInBracketSet="false" notes="" PrivateNotes="" name="PROVINCIA" label="PROVINCIA" qLabel="" indent="0" dataType="2" dataTypeLength="0" formatting="0" customFormatStr="" FormulaFunctionBodyCSharp="" suppType="0" SuppField="" suppFlags="" aggMethod="0" DocLinksAsString="" AggregationStr="None"/>
        <variable GUID="9cd8e588-7664-481c-af8e-c8c2df4cabb2" UVID="" BracketSourceVarGUID="" BracketFromVal="0" BracketToVal="0" BracketType="None" FirstInBracketSet="false" notes="" PrivateNotes="" name="MUNICIPIO" label="MUNICIPIO" qLabel="" indent="0" dataType="2" dataTypeLength="0" formatting="0" customFormatStr="" FormulaFunctionBodyCSharp="" suppType="0" SuppField="" suppFlags="" aggMethod="0" DocLinksAsString="" AggregationStr="None"/>
      </table>
    </tables>
  </GeoSurveyDataset>
  <SurveyDatasets>
    <SurveyDataset GUID="90fb8bdf-4684-452a-a68a-5253d90aaf66" SurveyDatasetTreeNodeExpanded="true" TablesTreeNodeExpanded="true" IterationsTreeNodeExpanded="false" DatasetsTreeNodeExpanded="true" Description="" Visible="false" abbreviation="SE" name="CED Tables" DisplayName="CED Tables">
      <DataBibliographicInfo/>
      <notes/>
      <PrivateNotes><![CDATA[]]></PrivateNotes>
      <Description><![CDATA[]]></Description>
      <datasets>
        <dataset GUID="e04539e2-bdf7-4af7-8a11-088d868a9bf8" GeoTypeName="SL010" DbConnString="Server=prime; database=; uid=none;pwd=none;Connect Timeout=1;Pooling=True" DbName="SEPE2020" GeoIdDbTableName="SEPE2020_SL010_001" IsCached="false" DbTableNamePrefix="SEPE2020_SL010_" DbPrimaryKey="SL010_FIPS" DbCopyCount="1"/>
        <dataset GUID="6f188f10-b66d-4c13-9c46-bdf5281d79fc" GeoTypeName="SL030" DbConnString="Server=prime; database=; uid=none;pwd=none;Connect Timeout=1;Pooling=True" DbName="SEPE2020" GeoIdDbTableName="SEPE2020_SL030_001" IsCached="false" DbTableNamePrefix="SEPE2020_SL030_" DbPrimaryKey="SL010_FIPS,SL030_FIPS" DbCopyCount="1"/>
        <dataset GUID="5c571fe0-e469-41c5-8cfd-7ae5956f8355" GeoTypeName="SL040" DbConnString="Server=prime; database=; uid=none;pwd=none;Connect Timeout=1;Pooling=True" DbName="SEPE2020" GeoIdDbTableName="SEPE2020_SL040_001" IsCached="false" DbTableNamePrefix="SEPE2020_SL040_" DbPrimaryKey="SL010_FIPS,SL030_FIPS,SL040_FIPS" DbCopyCount="1"/>
        <dataset GUID="e239b1a2-d580-435e-8923-3c1a688a8371" GeoTypeName="SL050" DbConnString="Server=prime; database=; uid=none;pwd=none;Connect Timeout=1;Pooling=True" DbName="SEPE2020" GeoIdDbTableName="SEPE2020_SL050_001" IsCached="false" DbTableNamePrefix="SEPE2020_SL050_" DbPrimaryKey="SL010_FIPS,SL030_FIPS,SL040_FIPS,SL050_FIPS" DbCopyCount="1"/>
      </datasets>
      <iterations/>
      <tables>
        <!--Insert SE tables here !!!-->
      </tables>
    </SurveyDataset>
    <SurveyDataset GUID="17c3edbb-1ef6-40b0-8158-ace12912bf69" SurveyDatasetTreeNodeExpanded="true" TablesTreeNodeExpanded="true" IterationsTreeNodeExpanded="false" DatasetsTreeNodeExpanded="true" Description="" Visible="true" abbreviation="ORG" name="Original Tables" DisplayName="Original Tables">
      <DataBibliographicInfo/>
      <notes/>
      <PrivateNotes><![CDATA[]]></PrivateNotes>
      <Description><![CDATA[]]></Description>
      <datasets>
        <dataset GUID="6aadd4ef-e5f6-4da2-8e85-ad9c09339cad" GeoTypeName="SL010" DbConnString="Server=prime; database=; uid=none;pwd=none;Connect Timeout=1;Pooling=True" DbName="SEPE2020" GeoIdDbTableName="SEPE2020_SL010_001" IsCached="false" DbTableNamePrefix="SEPE2020_SL010_" DbPrimaryKey="SL010_FIPS" DbCopyCount="1"/>
        <dataset GUID="0fea982b-26f0-4181-8276-50273048f2bf" GeoTypeName="SL030" DbConnString="Server=prime; database=; uid=none;pwd=none;Connect Timeout=1;Pooling=True" DbName="SEPE2020" GeoIdDbTableName="SEPE2020_SL030_001" IsCached="false" DbTableNamePrefix="SEPE2020_SL030_" DbPrimaryKey="SL010_FIPS,SL030_FIPS" DbCopyCount="1"/>
        <dataset GUID="64a66f23-6164-4d16-941c-b3e734311707" GeoTypeName="SL040" DbConnString="Server=prime; database=; uid=none;pwd=none;Connect Timeout=1;Pooling=True" DbName="SEPE2020" GeoIdDbTableName="SEPE2020_SL040_001" IsCached="false" DbTableNamePrefix="SEPE2020_SL040_" DbPrimaryKey="SL010_FIPS,SL030_FIPS,SL040_FIPS" DbCopyCount="1"/>
        <dataset GUID="14f64441-dc4f-4a2a-ab64-7f0b43067e2d" GeoTypeName="SL050" DbConnString="Server=prime; database=; uid=none;pwd=none;Connect Timeout=1;Pooling=True" DbName="SEPE2020" GeoIdDbTableName="SEPE2020_SL050_001" IsCached="false" DbTableNamePrefix="SEPE2020_SL050_" DbPrimaryKey="SL010_FIPS,SL030_FIPS,SL040_FIPS,SL050_FIPS" DbCopyCount="1"/>
      </datasets>
      <iterations/>
      <tables>
        <table GUID="0d49cb8d-83b1-4c28-9813-842f19e7b338" VariablesAreExclusive="false" DollarYear="0" PercentBaseMin="1" name="SEPE2020_001" displayName="SEPE2020_001" title="Paro registrado por sexo (media anual)" titleWrapped="Paro registrado por sexo (media anual)" universe="none" Visible="true" TreeNodeCollapsed="false" CategoryPriorityOrder="0" ShowOnFirstPageOfCategoryListing="false" DbTableSuffix="001" uniqueTableId="SEPE2020_001" notes="" PrivateNotes="" TableMapInfo="" titleShort="" VisibleInMaps="true" DocSectionLinks="" DataCategories="Empleo y desempleo;Actividad econ&#243;mica;" ProductTags="" FilterRuleName="" PaletteType="" PaletteInverse="false" PaletteName="" source="SEPE2018_001" DefaultColumnCaption="SEPE2018_001" samplingInfo="">
          <OutputFormat TableTitle="" TableUniverse="">
            <Columns/>
          </OutputFormat>
          <variable GUID="1bd3f766-5136-4904-9310-7f92fcb02c5b" UVID="" BracketSourceVarGUID="" BracketFromVal="0" BracketToVal="0" BracketType="None" FirstInBracketSet="false" notes="" PrivateNotes="" name="SEPE2020_001_SEPE_V1" label="Total personas en paro" qLabel="" indent="0" dataType="4" dataTypeLength="0" formatting="9" customFormatStr="" FormulaFunctionBodyCSharp="" suppType="0" SuppField="" suppFlags="" aggMethod="1" DocLinksAsString="" AggregationStr="Add" BubbleSizeHint="1" FR="DECIL_SPAIN" PN="" PT=""/>
          <variable GUID="f00394b8-cf18-425b-a9e8-df572def96db" UVID="" BracketSourceVarGUID="" BracketFromVal="0" BracketToVal="0" BracketType="None" FirstInBracketSet="false" notes="" PrivateNotes="" name="SEPE2020_001_SEPE_V2" label="Hombres" qLabel="" indent="1" dataType="4" dataTypeLength="0" formatting="9" customFormatStr="" FormulaFunctionBodyCSharp="" suppType="0" SuppField="" suppFlags="" aggMethod="1" DocLinksAsString="" AggregationStr="Add" BubbleSizeHint="1" FR="Sex_Spain2" PN="" PT=""/>
          <variable GUID="b206dc29-a2cb-44ba-9bc6-dd36e912acbe" UVID="" BracketSourceVarGUID="" BracketFromVal="0" BracketToVal="0" BracketType="None" FirstInBracketSet="false" notes="" PrivateNotes="" name="SEPE2020_001_SEPE_V3" label="Mujeres" qLabel="" indent="1" dataType="4" dataTypeLength="0" formatting="9" customFormatStr="" FormulaFunctionBodyCSharp="" suppType="0" SuppField="" suppFlags="" aggMethod="1" DocLinksAsString="" AggregationStr="Add" BubbleSizeHint="1" FR="Sex_Spain2" PN="" PT=""/>
        </table>
      </tables>
      <tables>
        <table GUID="6415442b-4697-46ac-baf9-9bfc077b58bf" VariablesAreExclusive="false" DollarYear="0" PercentBaseMin="1" name="SEPE2020_002" displayName="SEPE2020_002" title="Paro registrado por sexo y grupo de edad (media anual)" titleWrapped="Paro registrado por sexo y grupo de edad (media anual)" universe="none" Visible="true" TreeNodeCollapsed="false" CategoryPriorityOrder="0" ShowOnFirstPageOfCategoryListing="false" DbTableSuffix="002" uniqueTableId="SEPE2020_002" notes="" PrivateNotes="" TableMapInfo="" titleShort="" VisibleInMaps="true" DocSectionLinks="" DataCategories="Empleo y desempleo;Actividad econ&#243;mica;" ProductTags="" FilterRuleName="" PaletteType="" PaletteInverse="false" PaletteName="" source="SEPE2018_002" DefaultColumnCaption="SEPE2018_002" samplingInfo="">
          <OutputFormat TableTitle="" TableUniverse="">
            <Columns/>
          </OutputFormat>
          <variable GUID="5abb65f7-c179-4b1b-baff-e0aa822b7aaf" UVID="" BracketSourceVarGUID="" BracketFromVal="0" BracketToVal="0" BracketType="None" FirstInBracketSet="false" notes="" PrivateNotes="" name="SEPE2020_002_SEPE_V4" label="Total Personas en paro" qLabel="" indent="0" dataType="4" dataTypeLength="0" formatting="9" customFormatStr="" FormulaFunctionBodyCSharp="" suppType="0" SuppField="" suppFlags="" aggMethod="1" DocLinksAsString="" AggregationStr="Add" BubbleSizeHint="1" FR="DECIL_SPAIN" PN="" PT=""/>
          <variable GUID="f6cf158a-accb-41a1-9fb5-51ba04c6b6eb" UVID="" BracketSourceVarGUID="" BracketFromVal="0" BracketToVal="0" BracketType="None" FirstInBracketSet="false" notes="" PrivateNotes="" name="SEPE2020_002_SEPE_V5" label="Menores de 25 a&#241;os" qLabel="" indent="1" dataType="4" dataTypeLength="0" formatting="9" customFormatStr="" FormulaFunctionBodyCSharp="" suppType="0" SuppField="" suppFlags="" aggMethod="1" DocLinksAsString="" AggregationStr="Add" BubbleSizeHint="1" FR="DECIL_SPAIN" PN="" PT=""/>
          <variable GUID="592280c5-f6a8-481c-82c6-832c481c3988" UVID="" BracketSourceVarGUID="" BracketFromVal="0" BracketToVal="0" BracketType="None" FirstInBracketSet="false" notes="" PrivateNotes="" name="SEPE2020_002_SEPE_V6" label="25 y 44 a&#241;os" qLabel="" indent="1" dataType="4" dataTypeLength="0" formatting="9" customFormatStr="" FormulaFunctionBodyCSharp="" suppType="0" SuppField="" suppFlags="" aggMethod="1" DocLinksAsString="" AggregationStr="Add" BubbleSizeHint="1" FR="DECIL_SPAIN" PN="" PT=""/>
          <variable GUID="db792ef0-f0a9-49ed-97c3-5ef252005510" UVID="" BracketSourceVarGUID="" BracketFromVal="0" BracketToVal="0" BracketType="None" FirstInBracketSet="false" notes="" PrivateNotes="" name="SEPE2020_002_SEPE_V7" label="Mayores de 45 a&#241;os" qLabel="" indent="1" dataType="4" dataTypeLength="0" formatting="9" customFormatStr="" FormulaFunctionBodyCSharp="" suppType="0" SuppField="" suppFlags="" aggMethod="1" DocLinksAsString="" AggregationStr="Add" BubbleSizeHint="1" FR="DECIL_SPAIN" PN="" PT=""/>
          <variable GUID="e91ab9d2-a27f-4a9a-bbed-4b2e5e786af8" UVID="" BracketSourceVarGUID="" BracketFromVal="0" BracketToVal="0" BracketType="None" FirstInBracketSet="false" notes="" PrivateNotes="" name="SEPE2020_002_SEPE_V8" label="Hombres en paro" qLabel="" indent="0" dataType="4" dataTypeLength="0" formatting="9" customFormatStr="" FormulaFunctionBodyCSharp="" suppType="0" SuppField="" suppFlags="" aggMethod="1" DocLinksAsString="" AggregationStr="Add" BubbleSizeHint="1" FR="DECIL_SPAIN" PN="" PT=""/>
          <variable GUID="ec9b8e09-9af1-4f78-b38e-b2daf3e199bf" UVID="" BracketSourceVarGUID="" BracketFromVal="0" BracketToVal="0" BracketType="None" FirstInBracketSet="false" notes="" PrivateNotes="" name="SEPE2020_002_SEPE_V9" label="Menores de 25 a&#241;os" qLabel="" indent="1" dataType="4" dataTypeLength="0" formatting="9" customFormatStr="" FormulaFunctionBodyCSharp="" suppType="0" SuppField="" suppFlags="" aggMethod="1" DocLinksAsString="" AggregationStr="Add" BubbleSizeHint="1" FR="DECIL_SPAIN" PN="" PT=""/>
          <variable GUID="b5a3772a-fc03-4748-ab13-125b000dd094" UVID="" BracketSourceVarGUID="" BracketFromVal="0" BracketToVal="0" BracketType="None" FirstInBracketSet="false" notes="" PrivateNotes="" name="SEPE2020_002_SEPE_V10" label="25 y 44 a&#241;os" qLabel="" indent="1" dataType="4" dataTypeLength="0" formatting="9" customFormatStr="" FormulaFunctionBodyCSharp="" suppType="0" SuppField="" suppFlags="" aggMethod="1" DocLinksAsString="" AggregationStr="Add" BubbleSizeHint="1" FR="DECIL_SPAIN" PN="" PT=""/>
          <variable GUID="d3ee79aa-0292-475e-b274-cd36ec77d77c" UVID="" BracketSourceVarGUID="" BracketFromVal="0" BracketToVal="0" BracketType="None" FirstInBracketSet="false" notes="" PrivateNotes="" name="SEPE2020_002_SEPE_V11" label="Mayores de 45 a&#241;os" qLabel="" indent="1" dataType="4" dataTypeLength="0" formatting="9" customFormatStr="" FormulaFunctionBodyCSharp="" suppType="0" SuppField="" suppFlags="" aggMethod="1" DocLinksAsString="" AggregationStr="Add" BubbleSizeHint="1" FR="DECIL_SPAIN" PN="" PT=""/>
          <variable GUID="3535fad4-964d-4525-a893-7640dcd16c2a" UVID="" BracketSourceVarGUID="" BracketFromVal="0" BracketToVal="0" BracketType="None" FirstInBracketSet="false" notes="" PrivateNotes="" name="SEPE2020_002_SEPE_V12" label="Mujeres en paro" qLabel="" indent="0" dataType="4" dataTypeLength="0" formatting="9" customFormatStr="" FormulaFunctionBodyCSharp="" suppType="0" SuppField="" suppFlags="" aggMethod="1" DocLinksAsString="" AggregationStr="Add" BubbleSizeHint="1" FR="DECIL_SPAIN" PN="" PT=""/>
          <variable GUID="44a3f112-8b94-4ab6-8716-ce9a349334fe" UVID="" BracketSourceVarGUID="" BracketFromVal="0" BracketToVal="0" BracketType="None" FirstInBracketSet="false" notes="" PrivateNotes="" name="SEPE2020_002_SEPE_V13" label="Menores de 25 a&#241;os" qLabel="" indent="1" dataType="4" dataTypeLength="0" formatting="9" customFormatStr="" FormulaFunctionBodyCSharp="" suppType="0" SuppField="" suppFlags="" aggMethod="1" DocLinksAsString="" AggregationStr="Add" BubbleSizeHint="1" FR="DECIL_SPAIN" PN="" PT=""/>
          <variable GUID="9f438d97-5575-4932-a7e8-330f5ecef324" UVID="" BracketSourceVarGUID="" BracketFromVal="0" BracketToVal="0" BracketType="None" FirstInBracketSet="false" notes="" PrivateNotes="" name="SEPE2020_002_SEPE_V14" label="25 y 44 a&#241;os" qLabel="" indent="1" dataType="4" dataTypeLength="0" formatting="9" customFormatStr="" FormulaFunctionBodyCSharp="" suppType="0" SuppField="" suppFlags="" aggMethod="1" DocLinksAsString="" AggregationStr="Add" BubbleSizeHint="1" FR="DECIL_SPAIN" PN="" PT=""/>
          <variable GUID="36fad4cc-3a28-4ec6-bc38-c9e77e64a4a7" UVID="" BracketSourceVarGUID="" BracketFromVal="0" BracketToVal="0" BracketType="None" FirstInBracketSet="false" notes="" PrivateNotes="" name="SEPE2020_002_SEPE_V15" label="Mayores de 45 a&#241;os" qLabel="" indent="1" dataType="4" dataTypeLength="0" formatting="9" customFormatStr="" FormulaFunctionBodyCSharp="" suppType="0" SuppField="" suppFlags="" aggMethod="1" DocLinksAsString="" AggregationStr="Add" BubbleSizeHint="1" FR="DECIL_SPAIN" PN="" PT=""/>
          <variable GUID="d2753b00-c0dc-47cf-a8d2-d82cad7c0cfa" UVID="" BracketSourceVarGUID="" BracketFromVal="0" BracketToVal="0" BracketType="None" FirstInBracketSet="false" notes="" PrivateNotes="" name="SEPE2020_002_SEPE_V16" label="Paro menores de 25 a&#241;os" qLabel="" indent="0" dataType="7" dataTypeLength="0" formatting="9" customFormatStr="" FormulaFunctionBodyCSharp="" suppType="0" SuppField="" suppFlags="" aggMethod="1" DocLinksAsString="" AggregationStr="Add"/>
          <variable GUID="44670bdb-306a-4ff3-9652-0c100ed85229" UVID="" BracketSourceVarGUID="" BracketFromVal="0" BracketToVal="0" BracketType="None" FirstInBracketSet="false" notes="" PrivateNotes="" name="SEPE2020_002_SEPE_V17" label="Paro hombres menores de 25 a&#241;os" qLabel="" indent="1" dataType="7" dataTypeLength="0" formatting="9" customFormatStr="" FormulaFunctionBodyCSharp="" suppType="0" SuppField="" suppFlags="" aggMethod="1" DocLinksAsString="" AggregationStr="Add"/>
          <variable GUID="864758a6-63ad-4faa-8fc9-66bb04be31fb" UVID="" BracketSourceVarGUID="" BracketFromVal="0" BracketToVal="0" BracketType="None" FirstInBracketSet="false" notes="" PrivateNotes="" name="SEPE2020_002_SEPE_V18" label="Paro mujeres menores de 25 a&#241;os" qLabel="" indent="1" dataType="7" dataTypeLength="0" formatting="9" customFormatStr="" FormulaFunctionBodyCSharp="" suppType="0" SuppField="" suppFlags="" aggMethod="1" DocLinksAsString="" AggregationStr="Add"/>
          <variable GUID="9e38cb2f-9563-4c6d-82c2-dfd52b3d729b" UVID="" BracketSourceVarGUID="" BracketFromVal="0" BracketToVal="0" BracketType="None" FirstInBracketSet="false" notes="" PrivateNotes="" name="SEPE2020_002_SEPE_V19" label="Paro entre 25 y 44 a&#241;os" qLabel="" indent="0" dataType="7" dataTypeLength="0" formatting="9" customFormatStr="" FormulaFunctionBodyCSharp="" suppType="0" SuppField="" suppFlags="" aggMethod="1" DocLinksAsString="" AggregationStr="Add"/>
          <variable GUID="8b01ca13-fa6d-4761-909e-92ab90a68a70" UVID="" BracketSourceVarGUID="" BracketFromVal="0" BracketToVal="0" BracketType="None" FirstInBracketSet="false" notes="" PrivateNotes="" name="SEPE2020_002_SEPE_V20" label="Paro hombres entre 25 y 44 a&#241;os" qLabel="" indent="1" dataType="7" dataTypeLength="0" formatting="9" customFormatStr="" FormulaFunctionBodyCSharp="" suppType="0" SuppField="" suppFlags="" aggMethod="1" DocLinksAsString="" AggregationStr="Add"/>
          <variable GUID="4ded976f-3f98-4988-bbab-9fa03423c451" UVID="" BracketSourceVarGUID="" BracketFromVal="0" BracketToVal="0" BracketType="None" FirstInBracketSet="false" notes="" PrivateNotes="" name="SEPE2020_002_SEPE_V21" label="Paro mujeres entre 25 y 44 a&#241;os" qLabel="" indent="1" dataType="7" dataTypeLength="0" formatting="9" customFormatStr="" FormulaFunctionBodyCSharp="" suppType="0" SuppField="" suppFlags="" aggMethod="1" DocLinksAsString="" AggregationStr="Add"/>
          <variable GUID="0c271c36-00db-4058-b01d-3f665581119a" UVID="" BracketSourceVarGUID="" BracketFromVal="0" BracketToVal="0" BracketType="None" FirstInBracketSet="false" notes="" PrivateNotes="" name="SEPE2020_002_SEPE_V22" label="Paro mayores de 45 a&#241;os" qLabel="" indent="0" dataType="7" dataTypeLength="0" formatting="9" customFormatStr="" FormulaFunctionBodyCSharp="" suppType="0" SuppField="" suppFlags="" aggMethod="1" DocLinksAsString="" AggregationStr="Add"/>
          <variable GUID="17f314bf-22af-4f63-9006-4f8ea964d932" UVID="" BracketSourceVarGUID="" BracketFromVal="0" BracketToVal="0" BracketType="None" FirstInBracketSet="false" notes="" PrivateNotes="" name="SEPE2020_002_SEPE_V23" label="Paro hombres mayores de 45 a&#241;os" qLabel="" indent="1" dataType="7" dataTypeLength="0" formatting="9" customFormatStr="" FormulaFunctionBodyCSharp="" suppType="0" SuppField="" suppFlags="" aggMethod="1" DocLinksAsString="" AggregationStr="Add"/>
          <variable GUID="27f01727-2f20-4b00-b7d6-1e423922034b" UVID="" BracketSourceVarGUID="" BracketFromVal="0" BracketToVal="0" BracketType="None" FirstInBracketSet="false" notes="" PrivateNotes="" name="SEPE2020_002_SEPE_V24" label="Paro mujeres mayores de 45 a&#241;os" qLabel="" indent="1" dataType="7" dataTypeLength="0" formatting="9" customFormatStr="" FormulaFunctionBodyCSharp="" suppType="0" SuppField="" suppFlags="" aggMethod="1" DocLinksAsString="" AggregationStr="Add"/>
        </table>
      </tables>
      <tables>
        <table GUID="9501943d-2aff-4b98-b5c2-5865b326e8ad" VariablesAreExclusive="false" DollarYear="0" PercentBaseMin="1" name="SEPE2020_003" displayName="SEPE2020_003" title="Paro registrado por sector de actividad econ&#243;mica (media anual)" titleWrapped="Paro registrado por sector de actividad econ&#243;mica (media anual)" universe="none" Visible="true" TreeNodeCollapsed="false" CategoryPriorityOrder="0" ShowOnFirstPageOfCategoryListing="false" DbTableSuffix="003" uniqueTableId="SEPE2020_003" notes="" PrivateNotes="" TableMapInfo="" titleShort="" VisibleInMaps="true" DocSectionLinks="" DataCategories="Empleo y desempleo;Actividad econ&#243;mica;" ProductTags="" FilterRuleName="" PaletteType="" PaletteInverse="false" PaletteName="" source="SEPE2018_003" DefaultColumnCaption="SEPE2018_003" samplingInfo="">
          <OutputFormat TableTitle="" TableUniverse="">
            <Columns/>
          </OutputFormat>
          <variable GUID="b7aeb639-adbf-4372-8da3-141995e910f5" UVID="" BracketSourceVarGUID="" BracketFromVal="0" BracketToVal="0" BracketType="None" FirstInBracketSet="false" notes="" PrivateNotes="" name="SEPE2020_003_SEPE_V25" label="Personas en paro" qLabel="" indent="0" dataType="4" dataTypeLength="0" formatting="9" customFormatStr="" FormulaFunctionBodyCSharp="" suppType="0" SuppField="" suppFlags="" aggMethod="1" DocLinksAsString="" AggregationStr="Add" BubbleSizeHint="1" FR="DECIL_SPAIN" PN="" PT=""/>
          <variable GUID="affb467b-64a0-4604-8da5-21a9ea2feec9" UVID="" BracketSourceVarGUID="" BracketFromVal="0" BracketToVal="0" BracketType="None" FirstInBracketSet="false" notes="" PrivateNotes="" name="SEPE2020_003_SEPE_V26" label="Agricultura" qLabel="" indent="1" dataType="4" dataTypeLength="0" formatting="9" customFormatStr="" FormulaFunctionBodyCSharp="" suppType="0" SuppField="" suppFlags="" aggMethod="1" DocLinksAsString="" AggregationStr="Add" BubbleSizeHint="1" FR="DECIL_SPAIN" PN="" PT=""/>
          <variable GUID="cc6f63dc-2580-49be-bcaf-c274a5d8701a" UVID="" BracketSourceVarGUID="" BracketFromVal="0" BracketToVal="0" BracketType="None" FirstInBracketSet="false" notes="" PrivateNotes="" name="SEPE2020_003_SEPE_V27" label="Industria" qLabel="" indent="1" dataType="4" dataTypeLength="0" formatting="9" customFormatStr="" FormulaFunctionBodyCSharp="" suppType="0" SuppField="" suppFlags="" aggMethod="1" DocLinksAsString="" AggregationStr="Add" BubbleSizeHint="1" FR="DECIL_SPAIN" PN="" PT=""/>
          <variable GUID="1752db3a-bc3e-4569-b7d5-ad186b9a9e85" UVID="" BracketSourceVarGUID="" BracketFromVal="0" BracketToVal="0" BracketType="None" FirstInBracketSet="false" notes="" PrivateNotes="" name="SEPE2020_003_SEPE_V28" label="Construcci&#243;n" qLabel="" indent="1" dataType="4" dataTypeLength="0" formatting="9" customFormatStr="" FormulaFunctionBodyCSharp="" suppType="0" SuppField="" suppFlags="" aggMethod="1" DocLinksAsString="" AggregationStr="Add" BubbleSizeHint="1" FR="DECIL_SPAIN" PN="" PT=""/>
          <variable GUID="657f340c-05fb-4fe2-9763-3950b04e2f9c" UVID="" BracketSourceVarGUID="" BracketFromVal="0" BracketToVal="0" BracketType="None" FirstInBracketSet="false" notes="" PrivateNotes="" name="SEPE2020_003_SEPE_V29" label="Servicios" qLabel="" indent="1" dataType="4" dataTypeLength="0" formatting="9" customFormatStr="" FormulaFunctionBodyCSharp="" suppType="0" SuppField="" suppFlags="" aggMethod="1" DocLinksAsString="" AggregationStr="Add" BubbleSizeHint="1" FR="DECIL_SPAIN" PN="" PT=""/>
          <variable GUID="507f194a-ad42-4524-ba5e-00b160c840ba" UVID="" BracketSourceVarGUID="" BracketFromVal="0" BracketToVal="0" BracketType="None" FirstInBracketSet="false" notes="" PrivateNotes="" name="SEPE2020_003_SEPE_V30" label="Sin empleo anterior" qLabel="" indent="1" dataType="4" dataTypeLength="0" formatting="9" customFormatStr="" FormulaFunctionBodyCSharp="" suppType="0" SuppField="" suppFlags="" aggMethod="1" DocLinksAsString="" AggregationStr="Add" BubbleSizeHint="1" FR="DECIL_SPAIN" PN="" PT=""/>
        </table>
      </tables>
      <tables>
        <table GUID="8e9face7-a360-4a92-82f1-c6bf421ea237" VariablesAreExclusive="false" DollarYear="0" PercentBaseMin="1" name="SEPE2020_004" displayName="SEPE2020_004" title="Poblaci&#243;n en paro registrado por cada 100 habitantes seg&#250;n sexo y grupo de edad (media anual)" titleWrapped="Poblaci&#243;n en paro registrado por cada 100 habitantes seg&#250;n sexo y grupo de edad (media anual)" universe="none" Visible="true" TreeNodeCollapsed="false" CategoryPriorityOrder="0" ShowOnFirstPageOfCategoryListing="false" DbTableSuffix="004" uniqueTableId="SEPE2020_004" notes="" PrivateNotes="" TableMapInfo="" titleShort="" VisibleInMaps="true" DocSectionLinks="" DataCategories="Empleo y desempleo;Actividad econ&#243;mica;" ProductTags="" FilterRuleName="" PaletteType="" PaletteInverse="false" PaletteName="" source="SEPE2018_004" DefaultColumnCaption="SEPE2018_004" samplingInfo="">
          <OutputFormat TableTitle="" TableUniverse="">
            <Columns/>
          </OutputFormat>
          <variable GUID="48ac31a6-5d33-4cd9-be3a-bca76050db2c" UVID="" BracketSourceVarGUID="" BracketFromVal="0" BracketToVal="0" BracketType="None" FirstInBracketSet="false" notes="" PrivateNotes="" name="SEPE2020_004_SEPE_V31" label="Poblaci&#243;n en paro por cada 100 habitantes : entre 16 y 64 a&#241;os" qLabel="" indent="0" dataType="7" dataTypeLength="0" formatting="10" customFormatStr="" FormulaFunctionBodyCSharp="" suppType="0" SuppField="" suppFlags="" aggMethod="8" DocLinksAsString="" AggregationStr="Rate|||100000" BubbleSizeHint="1" FR="Unemployment" PN="" PT=""/>
          <variable GUID="95655198-7d90-4cb7-a362-232af48e4bae" UVID="" BracketSourceVarGUID="" BracketFromVal="0" BracketToVal="0" BracketType="None" FirstInBracketSet="false" notes="" PrivateNotes="" name="SEPE2020_004_SEPE_V32" label="Poblaci&#243;n en paro por cada 100 habitantes: entre 16 y 24 a&#241;os" qLabel="" indent="0" dataType="7" dataTypeLength="0" formatting="10" customFormatStr="" FormulaFunctionBodyCSharp="" suppType="0" SuppField="" suppFlags="" aggMethod="8" DocLinksAsString="" AggregationStr="Rate|||100000" BubbleSizeHint="1" FR="Unemployment" PN="" PT=""/>
          <variable GUID="c11880cd-2b14-476e-8dd0-ad07545ffa0e" UVID="" BracketSourceVarGUID="" BracketFromVal="0" BracketToVal="0" BracketType="None" FirstInBracketSet="false" notes="" PrivateNotes="" name="SEPE2020_004_SEPE_V33" label="Poblaci&#243;n en paro por cada 100 habitantes: entre 25 y 44 a&#241;os" qLabel="" indent="0" dataType="7" dataTypeLength="0" formatting="10" customFormatStr="" FormulaFunctionBodyCSharp="" suppType="0" SuppField="" suppFlags="" aggMethod="8" DocLinksAsString="" AggregationStr="Rate|||100000" BubbleSizeHint="1" FR="Unemployment" PN="" PT=""/>
          <variable GUID="fae02454-4483-4df5-b4db-880b065d51ee" UVID="" BracketSourceVarGUID="" BracketFromVal="0" BracketToVal="0" BracketType="None" FirstInBracketSet="false" notes="" PrivateNotes="" name="SEPE2020_004_SEPE_V34" label="Poblaci&#243;n en paro por cada 100 habitantes: 45 a&#241;os o m&#225;s" qLabel="" indent="0" dataType="7" dataTypeLength="0" formatting="10" customFormatStr="" FormulaFunctionBodyCSharp="" suppType="0" SuppField="" suppFlags="" aggMethod="8" DocLinksAsString="" AggregationStr="Rate|||100000" BubbleSizeHint="1" FR="Unemployment" PN="" PT=""/>
          <variable GUID="cdeacbaf-e509-4d07-bfe4-e9b64266a6b1" UVID="" BracketSourceVarGUID="" BracketFromVal="0" BracketToVal="0" BracketType="None" FirstInBracketSet="false" notes="" PrivateNotes="" name="SEPE2020_004_SEPE_V35" label="Poblaci&#243;n en paro por cada 100 habitantes: hombres entre 16 y 64 a&#241;os" qLabel="" indent="0" dataType="7" dataTypeLength="0" formatting="10" customFormatStr="" FormulaFunctionBodyCSharp="" suppType="0" SuppField="" suppFlags="" aggMethod="8" DocLinksAsString="" AggregationStr="Rate|||100000" BubbleSizeHint="1" FR="Unemployment" PN="" PT=""/>
          <variable GUID="bcc5fa0e-a453-4f3f-a6b0-8e07e4b45c68" UVID="" BracketSourceVarGUID="" BracketFromVal="0" BracketToVal="0" BracketType="None" FirstInBracketSet="false" notes="" PrivateNotes="" name="SEPE2020_004_SEPE_V36" label="Poblaci&#243;n en paro por cada 100 habitantes: hombres entre 16 y 24 a&#241;os" qLabel="" indent="0" dataType="7" dataTypeLength="0" formatting="10" customFormatStr="" FormulaFunctionBodyCSharp="" suppType="0" SuppField="" suppFlags="" aggMethod="8" DocLinksAsString="" AggregationStr="Rate|||100000" BubbleSizeHint="1" FR="Unemployment" PN="" PT=""/>
          <variable GUID="ded0af90-a637-4c74-aec3-04b08d911a89" UVID="" BracketSourceVarGUID="" BracketFromVal="0" BracketToVal="0" BracketType="None" FirstInBracketSet="false" notes="" PrivateNotes="" name="SEPE2020_004_SEPE_V37" label="Poblaci&#243;n en paro por cada 100 habitantes: hombres entre 25 y 44 a&#241;os" qLabel="" indent="0" dataType="7" dataTypeLength="0" formatting="10" customFormatStr="" FormulaFunctionBodyCSharp="" suppType="0" SuppField="" suppFlags="" aggMethod="8" DocLinksAsString="" AggregationStr="Rate|||100000" BubbleSizeHint="1" FR="Unemployment" PN="" PT=""/>
          <variable GUID="2cbdb56e-d8a6-421f-8529-93976fe7d97a" UVID="" BracketSourceVarGUID="" BracketFromVal="0" BracketToVal="0" BracketType="None" FirstInBracketSet="false" notes="" PrivateNotes="" name="SEPE2020_004_SEPE_V38" label="Poblaci&#243;n en paro por cada 100 habitantes: hombres 45 a&#241;os o m&#225;s" qLabel="" indent="0" dataType="7" dataTypeLength="0" formatting="10" customFormatStr="" FormulaFunctionBodyCSharp="" suppType="0" SuppField="" suppFlags="" aggMethod="8" DocLinksAsString="" AggregationStr="Rate|||100000" BubbleSizeHint="1" FR="Unemployment" PN="" PT=""/>
          <variable GUID="012a2370-a72f-4ec8-8b36-57d4da1574d9" UVID="" BracketSourceVarGUID="" BracketFromVal="0" BracketToVal="0" BracketType="None" FirstInBracketSet="false" notes="" PrivateNotes="" name="SEPE2020_004_SEPE_V39" label="Poblaci&#243;n en paro por cada 100 habitantes: mujeres entre 16 y 64 a&#241;os" qLabel="" indent="0" dataType="7" dataTypeLength="0" formatting="10" customFormatStr="" FormulaFunctionBodyCSharp="" suppType="0" SuppField="" suppFlags="" aggMethod="8" DocLinksAsString="" AggregationStr="Rate|||100000" BubbleSizeHint="1" FR="Unemployment" PN="" PT=""/>
          <variable GUID="dd7b30ee-a75c-4225-b82f-f0e76615c3a1" UVID="" BracketSourceVarGUID="" BracketFromVal="0" BracketToVal="0" BracketType="None" FirstInBracketSet="false" notes="" PrivateNotes="" name="SEPE2020_004_SEPE_V40" label="Poblaci&#243;n en paro por cada 100 habitantes: mujeres entre 16 y 24 a&#241;os" qLabel="" indent="0" dataType="7" dataTypeLength="0" formatting="10" customFormatStr="" FormulaFunctionBodyCSharp="" suppType="0" SuppField="" suppFlags="" aggMethod="8" DocLinksAsString="" AggregationStr="Rate|||100000" BubbleSizeHint="1" FR="Unemployment" PN="" PT=""/>
          <variable GUID="f771b47b-e577-4968-98e8-3c271ca15902" UVID="" BracketSourceVarGUID="" BracketFromVal="0" BracketToVal="0" BracketType="None" FirstInBracketSet="false" notes="" PrivateNotes="" name="SEPE2020_004_SEPE_V41" label="Poblaci&#243;n en paro por cada 100 habitantes: mujeres entre 25 y 44 a&#241;os" qLabel="" indent="0" dataType="7" dataTypeLength="0" formatting="10" customFormatStr="" FormulaFunctionBodyCSharp="" suppType="0" SuppField="" suppFlags="" aggMethod="8" DocLinksAsString="" AggregationStr="Rate|||100000" BubbleSizeHint="1" FR="Unemployment" PN="" PT=""/>
          <variable GUID="d938100b-66cc-4a76-9f01-8c7c1b8fd05d" UVID="" BracketSourceVarGUID="" BracketFromVal="0" BracketToVal="0" BracketType="None" FirstInBracketSet="false" notes="" PrivateNotes="" name="SEPE2020_004_SEPE_V42" label="Poblaci&#243;n en paro por cada 100 habitantes: mujeres 45 a&#241;os o m&#225;s" qLabel="" indent="0" dataType="7" dataTypeLength="0" formatting="10" customFormatStr="" FormulaFunctionBodyCSharp="" suppType="0" SuppField="" suppFlags="" aggMethod="8" DocLinksAsString="" AggregationStr="Rate|||100000" BubbleSizeHint="1" FR="Unemployment" PN="" PT=""/>
        </table>
      </tables>
    </SurveyDataset>
  </SurveyDatasets>
  <Categories>
    <string>Paro registrado 2020</string>
  </Categories>
</survey>
